streamlit_js_eval/__init__.py
streamlit_js_eval/index.html
streamlit_js_eval/__pycache__/__init__.cpython-312.pyc
streamlit_js_eval-1.0.0.dist-info/LICENSE
streamlit_js_eval-1.0.0.dist-info/METADATA
streamlit_js_eval-1.0.0.dist-info/WHEEL
streamlit_js_eval-1.0.0.dist-info/top_level.txt
streamlit_js_eval-1.0.0.dist-info/RECORD
