Metadata-Version: 2.1
Name: streamlit-js-eval
Version: 1.0.0
Summary: A custom Streamlit component to evaluate arbitrary Javascript expressions.
Home-page: https://github.com/aghasemi/streamlit_js_eval
Author: Alireza Ghasemi
Author-email: ghasemi.a.ir@gmail.com
Keywords: Python,Streamlit,JavaScript
Requires-Python: >=3.8
License-File: LICENSE
